MinHeap
