Metadata-Version: 2.1
Name: MinHeap
Version: 2.0
Summary: A min-Heap that utilizes numpy memmaps so memory consumption can be reduced.
Home-page: https://www.inventorsniche.com
Author: Harold J. Iwen
Author-email: inventorsniche349@gmail.com
License: MIT
Download-URL: https://github.com/Hiwen-STEM/MinHeap
Keywords: Binary_Tree,Heap,Tree,Min_Heap,Binary
Platform: UNKNOWN
Classifier: Intended Audience :: Developers
Classifier: Topic :: Software Development :: Build Tools
Classifier: License :: OSI Approved :: MIT License
Classifier: Programming Language :: Python :: 3.6
Classifier: Programming Language :: Python :: 3.7
Classifier: Programming Language :: Python :: 3.8
